{
  "courses": [
    {
      "id": 1,
      "title": "Introduction to Photography",
      "slug": "introduction-to-photography",
      "description": "Start your photography journey by learning essential camera settings, composition techniques, and lighting basics.",
      "price": 99.99,
      "instructor": "John Doe",
      "isFeatured": true,
      "image": "https://images.unsplash.com/photo-1630657942976-93950206fcc3?q=80&w=1029&auto=format&fit=crop&ixlib=rb-4.0.3&ixid=M3wxMjA3fDB8MHxwaG90by1wYWdlfHx8fGVufDB8fHx8fA%3D%3D"
    },
    {
      "id": 2,
      "title": "Portrait Photography",
      "slug": "portrait-photography",
      "description": "Capture stunning portraits by mastering lighting, posing, and camera settings.",
      "price": 109.99,
      "instructor": "Jane Smith",
      "isFeatured": false,
      "image": "https://images.unsplash.com/photo-1544005313-94ddf0286df2?q=80&w=1288&auto=format&fit=crop&ixlib=rb-4.0.3&ixid=M3wxMjA3fDB8MHxwaG90by1wYWdlfHx8fGVufDB8fHx8fA%3D%3D"
    },
    {
      "id": 3,
      "title": "Advanced Photo Editing",
      "slug": "advanced-photo-editing",
      "description": "Take your photos to the next level with advanced editing techniques using popular software.",
      "price": 119.99,
      "instructor": "Emily Johnson",
      "isFeatured": true,
      "image": "https://images.unsplash.com/photo-1609619385002-f40f1df9b7eb?q=80&w=1170&auto=format&fit=crop&ixlib=rb-4.0.3&ixid=M3wxMjA3fDB8MHxwaG90by1wYWdlfHx8fGVufDB8fHx8fA%3D%3D"
    },
    {
      "id": 4,
      "title": "Landscape Photography",
      "slug": "landscape-photography",
      "description": "Discover the secrets of breathtaking landscape photography, from composition to post-processing.",
      "price": 129.99,
      "instructor": "Mike Brown",
      "isFeatured": false,
      "image": "https://images.unsplash.com/photo-1604430456280-43f652c497aa?q=80&w=1170&auto=format&fit=crop&ixlib=rb-4.0.3&ixid=M3wxMjA3fDB8MHxwaG90by1wYWdlfHx8fGVufDB8fHx8fA%3D%3D"
    },
    {
      "id": 5,
      "title": "Wedding Photography",
      "slug": "wedding-photography",
      "description": "Learn to capture the magic of weddings with our comprehensive guide to wedding photography.",
      "price": 139.99,
      "instructor": "Chris Davis",
      "isFeatured": false,
      "image": "https://images.unsplash.com/photo-1533091090875-1ff4acc497dd?q=80&w=1169&auto=format&fit=crop&ixlib=rb-4.0.3&ixid=M3wxMjA3fDB8MHxwaG90by1wYWdlfHx8fGVufDB8fHx8fA%3D%3D"
    },
    {
      "id": 6,
      "title": "Graphic Design for Photographers",
      "slug": "graphic-design-for-photographers",
      "description": "Enhance your photography skills with essential graphic design principles and software techniques.",
      "price": 149.99,
      "instructor": "Alex Wilson",
      "isFeatured": true,
      "image": "https://plus.unsplash.com/premium_photo-1661411360156-3834fcb8ecba?q=80&w=1172&auto=format&fit=crop&ixlib=rb-4.0.3&ixid=M3wxMjA3fDB8MHxwaG90by1wYWdlfHx8fGVufDB8fHx8fA%3D%3D"
    },
    {
      "id": 7,
      "title": "Creative Photography Techniques",
      "slug": "creative-photography-techniques",
      "description": "Explore innovative photography techniques to unleash your creativity.",
      "price": 159.99,
      "instructor": "Samantha Miller",
      "isFeatured": false,
      "image": "https://images.unsplash.com/photo-1460661419201-fd4cecdf8a8b?q=80&w=1160&auto=format&fit=crop&ixlib=rb-4.0.3&ixid=M3wxMjA3fDB8MHxwaG90by1wYWdlfHx8fGVufDB8fHx8fA%3D%3D"
    },
    {
      "id": 8,
      "title": "Digital Art for Photographers",
      "slug": "digital-art-for-photographers",
      "description": "Blend photography and digital art to create stunning visual pieces.",
      "price": 169.99,
      "instructor": "Luke Harris",
      "isFeatured": true,
      "image": "https://images.unsplash.com/photo-1568602471122-7832951cc4c5?q=80&w=1170&auto=format&fit=crop&ixlib=rb-4.0.3&ixid=M3wxMjA3fDB8MHxwaG90by1wYWdlfHx8fGVufDB8fHx8fA%3D%3D"
    },
    {
      "id": 9,
      "title": "History of Photography",
      "slug": "history-of-photography",
      "description": "Delve into the rich history of photography from its beginnings to modern times.",
      "price": 179.99,
      "instructor": "Grace Lee",
      "isFeatured": false,
      "image": "https://plus.unsplash.com/premium_photo-1697729885210-41d99b8a8688?q=80&w=1170&auto=format&fit=crop&ixlib=rb-4.0.3&ixid=M3wxMjA3fDB8MHxwaG90by1wYWdlfHx8fGVufDB8fHx8fA%3D%3D"
    },
    {
      "id": 10,
      "title": "Fashion Photography",
      "slug": "fashion-photography",
      "description": "Capture the essence of fashion with techniques tailored for fashion photography.",
      "price": 189.99,
      "instructor": "Ethan Moore",
      "isFeatured": true,
      "image": "https://images.unsplash.com/photo-1573496371496-9971e371e4de?q=80&w=1374&auto=format&fit=crop&ixlib=rb-4.0.3&ixid=M3wxMjA3fDB8MHxwaG90by1wYWdlfHx8fGVufDB8fHx8fA%3D%3D"
    }
  ]
}
